LICENSE.txt
MANIFEST.in
README.rst
TODO.txt
setup.py
hspy.egg-info/PKG-INFO
hspy.egg-info/SOURCES.txt
hspy.egg-info/dependency_links.txt
hspy.egg-info/requires.txt
hspy.egg-info/top_level.txt
marketplace/__init__.py
marketplace/decorators.py
marketplace/logger.py
marketplace/request_supplement.py
marketplace/middleware/__init__.py
marketplace/middleware/anchor_fix.py
marketplace/middleware/auth.py
marketplace/middleware/debug_mode_logging.py
marketplace/middleware/error_goggles.py
marketplace/middleware/error_goggles_reset.css
marketplace/middleware/mock.html
marketplace/middleware/mock.py