Metadata-Version: 1.0
Name: hspy
Version: 1.6.3
Summary: Utilities to aide HubSpot Marketplace development
Home-page: https://github.com/HubSpot/hspy
Author: prior
Author-email: mprior@hubspot.com
License: LICENSE.txt
Download-URL: https://github.com/HubSpot/hspy/tarball/v1.6.3
Platform: any
